{
    "key": "taxonomy_680fc14c25efd",
    "title": "Event Formats",
    "menu_order": 0,
    "active": true,
    "taxonomy": "event-format",
    "object_type": [
        "recruitment-event"
    ],
    "advanced_configuration": 1,
    "import_source": "",
    "import_date": "",
    "labels": {
        "name": "Event Formats",
        "singular_name": "Event Format",
        "menu_name": "Event Format",
        "all_items": "All Event Formats",
        "edit_item": "Edit Event Format",
        "view_item": "View Event Format",
        "update_item": "Update Event Format",
        "add_new_item": "Add New Event Format",
        "new_item_name": "New Event Format Name",
        "parent_item": "Parent Event Format",
        "parent_item_colon": "Parent Event Format:",
        "search_items": "Search Event Format",
        "most_used": "",
        "not_found": "No meeting type found",
        "no_terms": "No meeting type",
        "name_field_description": "",
        "slug_field_description": "",
        "parent_field_description": "",
        "desc_field_description": "",
        "filter_by_item": "Filter by meeting type",
        "items_list_navigation": "Meeting Type list navigation",
        "items_list": "Meeting Type list",
        "back_to_items": "← Go to meeting type",
        "item_link": "Meeting Type Link",
        "item_link_description": "A link to a meeting type"
    },
    "description": "",
    "capabilities": {
        "manage_terms": "manage_categories",
        "edit_terms": "manage_categories",
        "delete_terms": "manage_categories",
        "assign_terms": "edit_posts"
    },
    "public": 1,
    "publicly_queryable": 0,
    "hierarchical": 1,
    "show_ui": 1,
    "show_in_menu": 1,
    "show_in_nav_menus": 1,
    "show_in_rest": 1,
    "rest_base": "",
    "rest_namespace": "wp\/v2",
    "rest_controller_class": "WP_REST_Terms_Controller",
    "show_tagcloud": 1,
    "show_in_quick_edit": 1,
    "show_admin_column": 1,
    "rewrite": {
        "permalink_rewrite": "taxonomy_key",
        "with_front": "1",
        "rewrite_hierarchical": "1"
    },
    "query_var": "taxonomy_key",
    "query_var_name": "",
    "default_term": {
        "default_term_enabled": "0"
    },
    "sort": 0,
    "meta_box": "default",
    "meta_box_cb": "",
    "meta_box_sanitize_cb": "",
    "modified": 1747418920
}
